ohm_mcp/__init__.py
ohm_mcp/server.py
ohm_mcp-1.0.1.dist-info/licenses/LICENSE
ohm_mcp-1.0.1.dist-info/METADATA
ohm_mcp-1.0.1.dist-info/WHEEL
ohm_mcp-1.0.1.dist-info/entry_points.txt
ohm_mcp-1.0.1.dist-info/top_level.txt
ohm_mcp-1.0.1.dist-info/RECORD
