Metadata-Version: 2.4
Name: ohm-mcp
Version: 1.0.1
Summary: AI-Powered Python Refactoring & Code Quality Assistant - MCP Server with AST-based analysis
Author-email: Murugaraj <murugarajr@gmail.com>
Maintainer-email: Murugaraj <murugarajr@gmail.com>
License-Expression: MIT
Project-URL: Homepage, https://www.ohm-mcp.dev
Keywords: mcp,model-context-protocol,refactoring,code-quality,ast,python,static-analysis,testing,automation,developer-tools
Classifier: Development Status :: 4 - Beta
Classifier: Intended Audience :: Developers
Classifier: Operating System :: OS Independent
Classifier: Programming Language :: Python :: 3
Classifier: Programming Language :: Python :: 3.9
Classifier: Programming Language :: Python :: 3.10
Classifier: Programming Language :: Python :: 3.11
Classifier: Programming Language :: Python :: 3.12
Classifier: Programming Language :: Python :: 3.13
Classifier: Topic :: Software Development :: Quality Assurance
Classifier: Topic :: Software Development :: Testing
Classifier: Topic :: Software Development :: Libraries :: Python Modules
Classifier: Topic :: Utilities
Requires-Python: >=3.9
License-File: LICENSE
Requires-Dist: mcp>=0.1.0
Dynamic: license-file
